{
  "BONKUSDT_SHORT": {
    "symbol": "BONKUSDT",
    "direction": "SHORT",
    "entry": 3.74e-06,
    "tp1": 3.696e-06,
    "tp2": 3.6652e-06,
    "tp3": 3.6301e-06,
    "sl": 3.784e-06,
    "score": 85,
    "risk_percent": 1.176,
    "opened_at": 1784117699,
    "last_checked_at": 1784119811,
    "tp1_hit": false,
    "tp2_hit": false,
    "tp3_hit": false,
    "breakeven_sl": null
  },
  "ONDOUSDT_LONG": {
    "symbol": "ONDOUSDT",
    "direction": "LONG",
    "entry": 0.329,
    "tp1": 0.3322871429,
    "tp2": 0.3342594286,
    "tp3": 0.3365604286,
    "sl": 0.3257128571,
    "score": 104,
    "risk_percent": 0.999,
    "source": "RADAR",
    "opened_at": 1784119989,
    "last_checked_at": 1784119989,
    "tp1_hit": false,
    "tp2_hit": false,
    "tp3_hit": false,
    "breakeven_sl": null
  },
  "ETHUSDT_LONG": {
    "symbol": "ETHUSDT",
    "direction": "LONG",
    "entry": 1904.31,
    "tp1": 1919.2854285714,
    "tp2": 1928.2706857143,
    "tp3": 1938.7534857143,
    "sl": 1889.3345714286,
    "score": 103,
    "risk_percent": 0.786,
    "source": "RADAR",
    "opened_at": 1784119990,
    "last_checked_at": 1784119990,
    "tp1_hit": false,
    "tp2_hit": false,
    "tp3_hit": false,
    "breakeven_sl": null
  },
  "XRPUSDT_LONG": {
    "symbol": "XRPUSDT",
    "direction": "LONG",
    "entry": 1.1153,
    "tp1": 1.1207442857,
    "tp2": 1.1240108571,
    "tp3": 1.1278218571,
    "sl": 1.1098557143,
    "score": 98,
    "risk_percent": 0.488,
    "source": "RADAR",
    "opened_at": 1784119991,
    "last_checked_at": 1784119991,
    "tp1_hit": false,
    "tp2_hit": false,
    "tp3_hit": false,
    "breakeven_sl": null
  },
  "PENGUUSDT_LONG": {
    "symbol": "PENGUUSDT",
    "direction": "LONG",
    "entry": 0.006208,
    "tp1": 0.0062669429,
    "tp2": 0.0063023086,
    "tp3": 0.0063435686,
    "sl": 0.0061490571,
    "score": 98,
    "risk_percent": 0.949,
    "source": "RADAR",
    "opened_at": 1784119993,
    "last_checked_at": 1784119993,
    "tp1_hit": false,
    "tp2_hit": false,
    "tp3_hit": false,
    "breakeven_sl": null
  },
  "ENAUSDT_LONG": {
    "symbol": "ENAUSDT",
    "direction": "LONG",
    "entry": 0.08437,
    "tp1": 0.0851975714,
    "tp2": 0.0856941143,
    "tp3": 0.0862734143,
    "sl": 0.0835424286,
    "score": 98,
    "risk_percent": 0.981,
    "source": "RADAR",
    "opened_at": 1784119994,
    "last_checked_at": 1784119994,
    "tp1_hit": false,
    "tp2_hit": false,
    "tp3_hit": false,
    "breakeven_sl": null
  }
}