{
  "last_open_summary": 1784067362,
  "total": {
    "signals": 9,
    "tp1": 1,
    "tp2": 2,
    "tp3": 1,
    "sl": 1,
    "be": 0
  },
  "coins": {
    "DYDXUSDT": {
      "signals": 0,
      "tp1": 0,
      "tp2": 1,
      "tp3": 1,
      "sl": 0,
      "be": 0
    },
    "HUSDT": {
      "signals": 0,
      "tp1": 0,
      "tp2": 0,
      "tp3": 0,
      "sl": 1,
      "be": 0
    },
    "NOTUSDT": {
      "signals": 2,
      "tp1": 0,
      "tp2": 0,
      "tp3": 0,
      "sl": 0,
      "be": 0
    },
    "SKYUSDT": {
      "signals": 1,
      "tp1": 0,
      "tp2": 0,
      "tp3": 0,
      "sl": 0,
      "be": 0
    },
    "LINKUSDT": {
      "signals": 1,
      "tp1": 0,
      "tp2": 0,
      "tp3": 0,
      "sl": 0,
      "be": 0
    },
    "RIVERUSDT": {
      "signals": 1,
      "tp1": 0,
      "tp2": 0,
      "tp3": 0,
      "sl": 0,
      "be": 0
    },
    "BICOUSDT": {
      "signals": 1,
      "tp1": 0,
      "tp2": 0,
      "tp3": 0,
      "sl": 0,
      "be": 0
    },
    "PIEVERSEUSDT": {
      "signals": 1,
      "tp1": 0,
      "tp2": 0,
      "tp3": 0,
      "sl": 0,
      "be": 0
    },
    "IBMUSDT": {
      "signals": 1,
      "tp1": 0,
      "tp2": 0,
      "tp3": 0,
      "sl": 0,
      "be": 0
    },
    "BLURUSDT": {
      "signals": 0,
      "tp1": 1,
      "tp2": 0,
      "tp3": 0,
      "sl": 0,
      "be": 0
    },
    "NIGHTUSDT": {
      "signals": 0,
      "tp1": 0,
      "tp2": 1,
      "tp3": 0,
      "sl": 0,
      "be": 0
    },
    "BLENDUSDT": {
      "signals": 1,
      "tp1": 0,
      "tp2": 0,
      "tp3": 0,
      "sl": 0,
      "be": 0
    }
  },
  "days": {
    "2026-07-15": {
      "signals": 9,
      "tp1": 1,
      "tp2": 2,
      "tp3": 1,
      "sl": 1,
      "be": 0,
      "coins": {
        "DYDXUSDT": {
          "signals": 0,
          "tp1": 0,
          "tp2": 1,
          "tp3": 1,
          "sl": 0,
          "be": 0
        },
        "HUSDT": {
          "signals": 0,
          "tp1": 0,
          "tp2": 0,
          "tp3": 0,
          "sl": 1,
          "be": 0
        },
        "NOTUSDT": {
          "signals": 2,
          "tp1": 0,
          "tp2": 0,
          "tp3": 0,
          "sl": 0,
          "be": 0
        },
        "SKYUSDT": {
          "signals": 1,
          "tp1": 0,
          "tp2": 0,
          "tp3": 0,
          "sl": 0,
          "be": 0
        },
        "LINKUSDT": {
          "signals": 1,
          "tp1": 0,
          "tp2": 0,
          "tp3": 0,
          "sl": 0,
          "be": 0
        },
        "RIVERUSDT": {
          "signals": 1,
          "tp1": 0,
          "tp2": 0,
          "tp3": 0,
          "sl": 0,
          "be": 0
        },
        "BICOUSDT": {
          "signals": 1,
          "tp1": 0,
          "tp2": 0,
          "tp3": 0,
          "sl": 0,
          "be": 0
        },
        "PIEVERSEUSDT": {
          "signals": 1,
          "tp1": 0,
          "tp2": 0,
          "tp3": 0,
          "sl": 0,
          "be": 0
        },
        "IBMUSDT": {
          "signals": 1,
          "tp1": 0,
          "tp2": 0,
          "tp3": 0,
          "sl": 0,
          "be": 0
        },
        "BLURUSDT": {
          "signals": 0,
          "tp1": 1,
          "tp2": 0,
          "tp3": 0,
          "sl": 0,
          "be": 0
        },
        "NIGHTUSDT": {
          "signals": 0,
          "tp1": 0,
          "tp2": 1,
          "tp3": 0,
          "sl": 0,
          "be": 0
        },
        "BLENDUSDT": {
          "signals": 1,
          "tp1": 0,
          "tp2": 0,
          "tp3": 0,
          "sl": 0,
          "be": 0
        }
      }
    }
  },
  "last_update": 1784067533
}