{
  "last_open_summary": 1783878359,
  "total": {
    "signals": 36,
    "tp1": 7,
    "tp2": 5,
    "tp3": 6,
    "sl": 21,
    "be": 4
  },
  "coins": {
    "AAVEUSDT": {
      "signals": 2,
      "tp1": 1,
      "tp2": 1,
      "tp3": 1,
      "sl": 0,
      "be": 0
    },
    "NVDAUSDT": {
      "signals": 1,
      "tp1": 1,
      "tp2": 1,
      "tp3": 1,
      "sl": 0,
      "be": 0
    },
    "KGENUSDT": {
      "signals": 1,
      "tp1": 0,
      "tp2": 1,
      "tp3": 1,
      "sl": 0,
      "be": 0
    },
    "TRUSTUSDT": {
      "signals": 1,
      "tp1": 0,
      "tp2": 0,
      "tp3": 0,
      "sl": 0,
      "be": 0
    },
    "EGLDUSDT": {
      "signals": 1,
      "tp1": 0,
      "tp2": 0,
      "tp3": 0,
      "sl": 1,
      "be": 0
    },
    "SYRUPUSDT": {
      "signals": 0,
      "tp1": 0,
      "tp2": 0,
      "tp3": 0,
      "sl": 1,
      "be": 0
    },
    "XAGUSDT": {
      "signals": 3,
      "tp1": 0,
      "tp2": 0,
      "tp3": 0,
      "sl": 1,
      "be": 0
    },
    "RIVERUSDT": {
      "signals": 2,
      "tp1": 1,
      "tp2": 0,
      "tp3": 0,
      "sl": 1,
      "be": 0
    },
    "TURBOUSDT": {
      "signals": 1,
      "tp1": 0,
      "tp2": 0,
      "tp3": 0,
      "sl": 0,
      "be": 0
    },
    "ZECUSDT": {
      "signals": 0,
      "tp1": 0,
      "tp2": 1,
      "tp3": 1,
      "sl": 0,
      "be": 0
    },
    "XLMUSDT": {
      "signals": 0,
      "tp1": 0,
      "tp2": 0,
      "tp3": 0,
      "sl": 0,
      "be": 1
    },
    "KITEUSDT": {
      "signals": 1,
      "tp1": 0,
      "tp2": 0,
      "tp3": 0,
      "sl": 1,
      "be": 0
    },
    "BRETTUSDT": {
      "signals": 0,
      "tp1": 0,
      "tp2": 0,
      "tp3": 0,
      "sl": 1,
      "be": 0
    },
    "0GUSDT": {
      "signals": 0,
      "tp1": 1,
      "tp2": 1,
      "tp3": 1,
      "sl": 0,
      "be": 0
    },
    "JTOUSDT": {
      "signals": 0,
      "tp1": 0,
      "tp2": 0,
      "tp3": 0,
      "sl": 1,
      "be": 0
    },
    "UNIUSDT": {
      "signals": 1,
      "tp1": 0,
      "tp2": 0,
      "tp3": 0,
      "sl": 1,
      "be": 0
    },
    "SHELLUSDT": {
      "signals": 1,
      "tp1": 0,
      "tp2": 0,
      "tp3": 0,
      "sl": 0,
      "be": 0
    },
    "XTZUSDT": {
      "signals": 1,
      "tp1": 0,
      "tp2": 0,
      "tp3": 0,
      "sl": 1,
      "be": 0
    },
    "ACTUSDT": {
      "signals": 1,
      "tp1": 0,
      "tp2": 0,
      "tp3": 0,
      "sl": 1,
      "be": 0
    },
    "BSBUSDT": {
      "signals": 1,
      "tp1": 0,
      "tp2": 0,
      "tp3": 0,
      "sl": 0,
      "be": 1
    },
    "XAUUSDT": {
      "signals": 1,
      "tp1": 0,
      "tp2": 0,
      "tp3": 0,
      "sl": 1,
      "be": 0
    },
    "ZBTUSDT": {
      "signals": 2,
      "tp1": 0,
      "tp2": 0,
      "tp3": 0,
      "sl": 1,
      "be": 0
    },
    "MERLUSDT": {
      "signals": 0,
      "tp1": 0,
      "tp2": 0,
      "tp3": 0,
      "sl": 1,
      "be": 0
    },
    "MEMEUSDT": {
      "signals": 0,
      "tp1": 0,
      "tp2": 0,
      "tp3": 0,
      "sl": 1,
      "be": 0
    },
    "ZAMAUSDT": {
      "signals": 2,
      "tp1": 0,
      "tp2": 0,
      "tp3": 0,
      "sl": 0,
      "be": 0
    },
    "ADBEUSDT": {
      "signals": 1,
      "tp1": 0,
      "tp2": 0,
      "tp3": 0,
      "sl": 1,
      "be": 0
    },
    "RLSUSDT": {
      "signals": 3,
      "tp1": 0,
      "tp2": 0,
      "tp3": 0,
      "sl": 0,
      "be": 0
    },
    "WLFIUSDT": {
      "signals": 0,
      "tp1": 0,
      "tp2": 0,
      "tp3": 0,
      "sl": 0,
      "be": 1
    },
    "SPACEUSDT": {
      "signals": 1,
      "tp1": 0,
      "tp2": 0,
      "tp3": 0,
      "sl": 0,
      "be": 0
    },
    "ZROUSDT": {
      "signals": 1,
      "tp1": 1,
      "tp2": 0,
      "tp3": 0,
      "sl": 0,
      "be": 0
    },
    "GPSUSDT": {
      "signals": 1,
      "tp1": 0,
      "tp2": 0,
      "tp3": 0,
      "sl": 1,
      "be": 0
    },
    "PIPPINUSDT": {
      "signals": 0,
      "tp1": 0,
      "tp2": 0,
      "tp3": 0,
      "sl": 1,
      "be": 0
    },
    "BERAUSDT": {
      "signals": 0,
      "tp1": 1,
      "tp2": 0,
      "tp3": 0,
      "sl": 0,
      "be": 0
    },
    "ENSOUSDT": {
      "signals": 0,
      "tp1": 0,
      "tp2": 0,
      "tp3": 0,
      "sl": 1,
      "be": 0
    },
    "ANTHROPICUSDT": {
      "signals": 1,
      "tp1": 0,
      "tp2": 0,
      "tp3": 0,
      "sl": 0,
      "be": 0
    },
    "METUSDT": {
      "signals": 1,
      "tp1": 0,
      "tp2": 0,
      "tp3": 0,
      "sl": 0,
      "be": 0
    },
    "EWTUSDT": {
      "signals": 0,
      "tp1": 0,
      "tp2": 0,
      "tp3": 0,
      "sl": 1,
      "be": 0
    },
    "JELLYJELLYUSDT": {
      "signals": 0,
      "tp1": 0,
      "tp2": 0,
      "tp3": 0,
      "sl": 0,
      "be": 1
    },
    "JUPUSDT": {
      "signals": 1,
      "tp1": 0,
      "tp2": 0,
      "tp3": 0,
      "sl": 0,
      "be": 0
    },
    "IRYSUSDT": {
      "signals": 0,
      "tp1": 0,
      "tp2": 0,
      "tp3": 0,
      "sl": 1,
      "be": 0
    },
    "LRCUSDT": {
      "signals": 0,
      "tp1": 0,
      "tp2": 0,
      "tp3": 1,
      "sl": 0,
      "be": 0
    },
    "ARKMUSDT": {
      "signals": 1,
      "tp1": 0,
      "tp2": 0,
      "tp3": 0,
      "sl": 0,
      "be": 0
    },
    "SOONUSDT": {
      "signals": 1,
      "tp1": 0,
      "tp2": 0,
      "tp3": 0,
      "sl": 0,
      "be": 0
    },
    "ACUUSDT": {
      "signals": 1,
      "tp1": 0,
      "tp2": 0,
      "tp3": 0,
      "sl": 0,
      "be": 0
    },
    "CBRSUSDT": {
      "signals": 0,
      "tp1": 1,
      "tp2": 0,
      "tp3": 0,
      "sl": 0,
      "be": 0
    },
    "MEGAUSDT": {
      "signals": 0,
      "tp1": 0,
      "tp2": 0,
      "tp3": 0,
      "sl": 1,
      "be": 0
    }
  },
  "days": {
    "2026-07-12": {
      "signals": 36,
      "tp1": 7,
      "tp2": 5,
      "tp3": 6,
      "sl": 21,
      "be": 4,
      "coins": {
        "AAVEUSDT": {
          "signals": 2,
          "tp1": 1,
          "tp2": 1,
          "tp3": 1,
          "sl": 0,
          "be": 0
        },
        "NVDAUSDT": {
          "signals": 1,
          "tp1": 1,
          "tp2": 1,
          "tp3": 1,
          "sl": 0,
          "be": 0
        },
        "KGENUSDT": {
          "signals": 1,
          "tp1": 0,
          "tp2": 1,
          "tp3": 1,
          "sl": 0,
          "be": 0
        },
        "TRUSTUSDT": {
          "signals": 1,
          "tp1": 0,
          "tp2": 0,
          "tp3": 0,
          "sl": 0,
          "be": 0
        },
        "EGLDUSDT": {
          "signals": 1,
          "tp1": 0,
          "tp2": 0,
          "tp3": 0,
          "sl": 1,
          "be": 0
        },
        "SYRUPUSDT": {
          "signals": 0,
          "tp1": 0,
          "tp2": 0,
          "tp3": 0,
          "sl": 1,
          "be": 0
        },
        "XAGUSDT": {
          "signals": 3,
          "tp1": 0,
          "tp2": 0,
          "tp3": 0,
          "sl": 1,
          "be": 0
        },
        "RIVERUSDT": {
          "signals": 2,
          "tp1": 1,
          "tp2": 0,
          "tp3": 0,
          "sl": 1,
          "be": 0
        },
        "TURBOUSDT": {
          "signals": 1,
          "tp1": 0,
          "tp2": 0,
          "tp3": 0,
          "sl": 0,
          "be": 0
        },
        "ZECUSDT": {
          "signals": 0,
          "tp1": 0,
          "tp2": 1,
          "tp3": 1,
          "sl": 0,
          "be": 0
        },
        "XLMUSDT": {
          "signals": 0,
          "tp1": 0,
          "tp2": 0,
          "tp3": 0,
          "sl": 0,
          "be": 1
        },
        "KITEUSDT": {
          "signals": 1,
          "tp1": 0,
          "tp2": 0,
          "tp3": 0,
          "sl": 1,
          "be": 0
        },
        "BRETTUSDT": {
          "signals": 0,
          "tp1": 0,
          "tp2": 0,
          "tp3": 0,
          "sl": 1,
          "be": 0
        },
        "0GUSDT": {
          "signals": 0,
          "tp1": 1,
          "tp2": 1,
          "tp3": 1,
          "sl": 0,
          "be": 0
        },
        "JTOUSDT": {
          "signals": 0,
          "tp1": 0,
          "tp2": 0,
          "tp3": 0,
          "sl": 1,
          "be": 0
        },
        "UNIUSDT": {
          "signals": 1,
          "tp1": 0,
          "tp2": 0,
          "tp3": 0,
          "sl": 1,
          "be": 0
        },
        "SHELLUSDT": {
          "signals": 1,
          "tp1": 0,
          "tp2": 0,
          "tp3": 0,
          "sl": 0,
          "be": 0
        },
        "XTZUSDT": {
          "signals": 1,
          "tp1": 0,
          "tp2": 0,
          "tp3": 0,
          "sl": 1,
          "be": 0
        },
        "ACTUSDT": {
          "signals": 1,
          "tp1": 0,
          "tp2": 0,
          "tp3": 0,
          "sl": 1,
          "be": 0
        },
        "BSBUSDT": {
          "signals": 1,
          "tp1": 0,
          "tp2": 0,
          "tp3": 0,
          "sl": 0,
          "be": 1
        },
        "XAUUSDT": {
          "signals": 1,
          "tp1": 0,
          "tp2": 0,
          "tp3": 0,
          "sl": 1,
          "be": 0
        },
        "ZBTUSDT": {
          "signals": 2,
          "tp1": 0,
          "tp2": 0,
          "tp3": 0,
          "sl": 1,
          "be": 0
        },
        "MERLUSDT": {
          "signals": 0,
          "tp1": 0,
          "tp2": 0,
          "tp3": 0,
          "sl": 1,
          "be": 0
        },
        "MEMEUSDT": {
          "signals": 0,
          "tp1": 0,
          "tp2": 0,
          "tp3": 0,
          "sl": 1,
          "be": 0
        },
        "ZAMAUSDT": {
          "signals": 2,
          "tp1": 0,
          "tp2": 0,
          "tp3": 0,
          "sl": 0,
          "be": 0
        },
        "ADBEUSDT": {
          "signals": 1,
          "tp1": 0,
          "tp2": 0,
          "tp3": 0,
          "sl": 1,
          "be": 0
        },
        "RLSUSDT": {
          "signals": 3,
          "tp1": 0,
          "tp2": 0,
          "tp3": 0,
          "sl": 0,
          "be": 0
        },
        "WLFIUSDT": {
          "signals": 0,
          "tp1": 0,
          "tp2": 0,
          "tp3": 0,
          "sl": 0,
          "be": 1
        },
        "SPACEUSDT": {
          "signals": 1,
          "tp1": 0,
          "tp2": 0,
          "tp3": 0,
          "sl": 0,
          "be": 0
        },
        "ZROUSDT": {
          "signals": 1,
          "tp1": 1,
          "tp2": 0,
          "tp3": 0,
          "sl": 0,
          "be": 0
        },
        "GPSUSDT": {
          "signals": 1,
          "tp1": 0,
          "tp2": 0,
          "tp3": 0,
          "sl": 1,
          "be": 0
        },
        "PIPPINUSDT": {
          "signals": 0,
          "tp1": 0,
          "tp2": 0,
          "tp3": 0,
          "sl": 1,
          "be": 0
        },
        "BERAUSDT": {
          "signals": 0,
          "tp1": 1,
          "tp2": 0,
          "tp3": 0,
          "sl": 0,
          "be": 0
        },
        "ENSOUSDT": {
          "signals": 0,
          "tp1": 0,
          "tp2": 0,
          "tp3": 0,
          "sl": 1,
          "be": 0
        },
        "ANTHROPICUSDT": {
          "signals": 1,
          "tp1": 0,
          "tp2": 0,
          "tp3": 0,
          "sl": 0,
          "be": 0
        },
        "METUSDT": {
          "signals": 1,
          "tp1": 0,
          "tp2": 0,
          "tp3": 0,
          "sl": 0,
          "be": 0
        },
        "EWTUSDT": {
          "signals": 0,
          "tp1": 0,
          "tp2": 0,
          "tp3": 0,
          "sl": 1,
          "be": 0
        },
        "JELLYJELLYUSDT": {
          "signals": 0,
          "tp1": 0,
          "tp2": 0,
          "tp3": 0,
          "sl": 0,
          "be": 1
        },
        "JUPUSDT": {
          "signals": 1,
          "tp1": 0,
          "tp2": 0,
          "tp3": 0,
          "sl": 0,
          "be": 0
        },
        "IRYSUSDT": {
          "signals": 0,
          "tp1": 0,
          "tp2": 0,
          "tp3": 0,
          "sl": 1,
          "be": 0
        },
        "LRCUSDT": {
          "signals": 0,
          "tp1": 0,
          "tp2": 0,
          "tp3": 1,
          "sl": 0,
          "be": 0
        },
        "ARKMUSDT": {
          "signals": 1,
          "tp1": 0,
          "tp2": 0,
          "tp3": 0,
          "sl": 0,
          "be": 0
        },
        "SOONUSDT": {
          "signals": 1,
          "tp1": 0,
          "tp2": 0,
          "tp3": 0,
          "sl": 0,
          "be": 0
        },
        "ACUUSDT": {
          "signals": 1,
          "tp1": 0,
          "tp2": 0,
          "tp3": 0,
          "sl": 0,
          "be": 0
        },
        "CBRSUSDT": {
          "signals": 0,
          "tp1": 1,
          "tp2": 0,
          "tp3": 0,
          "sl": 0,
          "be": 0
        },
        "MEGAUSDT": {
          "signals": 0,
          "tp1": 0,
          "tp2": 0,
          "tp3": 0,
          "sl": 1,
          "be": 0
        }
      }
    }
  },
  "last_update": 1783881762
}